notifications_android_tv/__init__.py
notifications_android_tv/const.py
notifications_android_tv/exceptions.py
notifications_android_tv/helpers.py
notifications_android_tv/notifier.py
notifications_android_tv-1.2.2.dist-info/LICENSE
notifications_android_tv-1.2.2.dist-info/METADATA
notifications_android_tv-1.2.2.dist-info/WHEEL
notifications_android_tv-1.2.2.dist-info/RECORD
