Metadata-Version: 2.1
Name: notifications-android-tv
Version: 1.2.2
Summary: Python API for sending notifications to Android/Fire TVs
Home-page: https://github.com/engrbm87/notifications_android_tv
License: MIT
Author: Rami Mosleh
Author-email: engrbm87@gmail.com
Requires-Python: >=3.10,<4.0
Classifier: Development Status :: 3 - Alpha
Classifier: Environment :: Console
Classifier: Intended Audience :: Developers
Classifier: License :: OSI Approved :: MIT License
Classifier: Operating System :: MacOS :: MacOS X
Classifier: Operating System :: Microsoft :: Windows
Classifier: Operating System :: POSIX
Classifier: Programming Language :: Python :: 3
Classifier: Programming Language :: Python :: 3.10
Classifier: Programming Language :: Python :: 3.11
Classifier: Programming Language :: Python :: 3.12
Classifier: Topic :: Utilities
Requires-Dist: httpx (>=0.27.0,<0.28.0)
Project-URL: Repository, https://github.com/engrbm87/notifications_android_tv/releases
